software_release/__init__.py
software_release/abstract_commit_generator.py
software_release/angular_parser.py
software_release/branch_checker.py
software_release/branch_checker_interface.py
software_release/branch_interface.py
software_release/bump_determination_interface.py
software_release/cli.py
software_release/commit_generator.py
software_release/commit_generator_interface.py
software_release/commit_interface.py
software_release/component_renderer.py
software_release/config_reader.py
software_release/git_status.py
software_release/git_status_factory.py
software_release/git_status_interface.py
software_release/head_interface.py
software_release/new_release.py
software_release/node_interface.py
software_release/previous_release.py
software_release/pull_request.py
software_release/push_active_branch.py
software_release/push_active_branch_interface.py
software_release/py.typed
software_release/release_finder.py
software_release/release_wizard.py
software_release/repository.py
software_release/repository_factory.py
software_release/repository_interface.py
software_release/utils.py
software_release/version_bump_type.py
software_release/version_class.py
software_release/version_determination.py
software_release/app_commands/__init__.py
software_release/app_commands/command_commit_changes.py
software_release/app_commands/command_find_pr_online.py
software_release/app_commands/command_get_pr_title.py
software_release/app_commands/command_git_tag.py
software_release/app_commands/command_new_release.py
software_release/app_commands/command_node.py
software_release/app_commands/command_previous_release.py
software_release/app_commands/command_pull_branch.py
software_release/app_commands/command_pull_request.py
software_release/app_commands/command_push_branch.py
software_release/app_commands/command_push_tag.py
software_release/app_commands/command_render.py
software_release/app_commands/command_update_file.py
software_release/app_commands/command_wait_for_pr_approval.py
software_release-0.1.0.dist-info/METADATA
software_release-0.1.0.dist-info/WHEEL
software_release-0.1.0.dist-info/entry_points.txt
software_release-0.1.0.dist-info/top_level.txt
software_release-0.1.0.dist-info/RECORD
