Metadata-Version: 2.1
Name: software-release
Version: 0.1.0
Summary: Automate Releasing of Software, following Semantic Versioning
Home-page: https://github.com/boromir674/software-release
Download-URL: https://github.com/boromir674/software-release/archive/v0.1.0.tar.gz
Author: Konstantinos Lampridis
Author-email: k.lampridis@hotmail.com
License: AGPLv3
Project-URL: Bug Tracker, https://github.com/software-release/issues
Project-URL: CI: Github Actions, https://github.com/boromir674/software-release/actions
Project-URL: Documentation, https://software-release.readthedocs.io/
Project-URL: Source Code, https://github.com/boromir674/software-release
Keywords: python package
Platform: Linux
Platform: Darwin
Classifier: Development Status :: 5 - Production/Stable
Classifier: Intended Audience :: Developers
Classifier: Intended Audience :: End Users/Desktop
Classifier: Intended Audience :: Science/Research
Classifier: License :: OSI Approved :: GNU Affero General Public License v3
Classifier: Natural Language :: English
Classifier: Operating System :: Unix
Classifier: Programming Language :: Python
Classifier: Programming Language :: Python :: 3.8
Classifier: Topic :: Software Development
Classifier: Topic :: Software Development :: Libraries :: Python Modules
Classifier: Topic :: System :: Software Distribution
Classifier: Typing :: Typed
Requires-Python: >=3.6
Requires-Dist: attrs
Requires-Dist: click
Requires-Dist: gitpython
Requires-Dist: PyInquirer
Requires-Dist: semver
Requires-Dist: software-patterns
Requires-Dist: PyGithub
Provides-Extra: docs
Requires-Dist: furo (>=2021.08.31) ; extra == 'docs'
Requires-Dist: sphinx (~=4.0) ; extra == 'docs'
Requires-Dist: sphinx-argparse-cli (>=1.5) ; extra == 'docs'
Requires-Dist: sphinx-autodoc-typehints (>=1.10) ; extra == 'docs'
Provides-Extra: test
Requires-Dist: pytest (>=6.2.4) ; extra == 'test'
Requires-Dist: pytest-cov (>=2.12) ; extra == 'test'
Requires-Dist: pytest-xdist (>=1.34) ; extra == 'test'
Provides-Extra: typing
Requires-Dist: mypy ; extra == 'typing'
